STPN/__init__.py
STPN/metrics.py
STPN/time_func.py
STPN/util.py
STPN-0.0.5.dist-info/LICENSE
STPN-0.0.5.dist-info/METADATA
STPN-0.0.5.dist-info/WHEEL
STPN-0.0.5.dist-info/top_level.txt
STPN-0.0.5.dist-info/RECORD
