Metadata-Version: 2.1
Name: STPN
Version: 0.0.5
Summary: Library for Spatiotemporal Pattern Network
Home-page: https://github.com/tsyong98/STPN
Author: Sin Yong Tan
Author-email: tsyong98@gmail.com
License: UNKNOWN
Project-URL: Bug Tracker, https://github.com/tsyong98/STPN/issues
Platform: UNKNOWN
Classifier: Programming Language :: Python :: 3
Classifier: License :: OSI Approved :: MIT License
Classifier: Operating System :: OS Independent
Requires-Python: >=3.6
License-File: LICENSE
Requires-Dist: numpy
Requires-Dist: pandas
Requires-Dist: matplotlib
Requires-Dist: sklearn
